networksdb/__init__.py
networksdb/networksdb.py
networksdb-1.0.3.dist-info/LICENSE
networksdb-1.0.3.dist-info/METADATA
networksdb-1.0.3.dist-info/WHEEL
networksdb-1.0.3.dist-info/top_level.txt
networksdb-1.0.3.dist-info/RECORD
