Metadata-Version: 2.1
Name: networksdb
Version: 1.0.3
Summary: Official Python library for NetworksDB.io
Home-page: https://networksdb.io
Author: NetworksDB
Author-email: contact@networksdb.io
License: Apache License 2.0
Platform: UNKNOWN
Requires-Dist: requests
Requires-Dist: attrdict
